{"nodes": [{"id": "d_rl_project_data_cleaning_openenv_backend_services_cleaning_service_py", "label": "cleaning_service.py", "file_type": "code", "source_file": "D:\\RL-PROJECT\\data-cleaning-openenv\\backend\\services\\cleaning_service.py", "source_location": "L1"}, {"id": "cleaning_service_cleaningservice", "label": "CleaningService", "file_type": "code", "source_file": "D:\\RL-PROJECT\\data-cleaning-openenv\\backend\\services\\cleaning_service.py", "source_location": "L28"}, {"id": "cleaning_service_cleaningservice_init", "label": ".__init__()", "file_type": "code", "source_file": "D:\\RL-PROJECT\\data-cleaning-openenv\\backend\\services\\cleaning_service.py", "source_location": "L31"}, {"id": "cleaning_service_cleaningservice_clean_existing_job", "label": ".clean_existing_job()", "file_type": "code", "source_file": "D:\\RL-PROJECT\\data-cleaning-openenv\\backend\\services\\cleaning_service.py", "source_location": "L35"}, {"id": "cleaning_service_cleaningservice_clean_batch", "label": ".clean_batch()", "file_type": "code", "source_file": "D:\\RL-PROJECT\\data-cleaning-openenv\\backend\\services\\cleaning_service.py", "source_location": "L85"}, {"id": "cleaning_service_cleaningservice_get_next_action", "label": ".get_next_action()", "file_type": "code", "source_file": "D:\\RL-PROJECT\\data-cleaning-openenv\\backend\\services\\cleaning_service.py", "source_location": "L103"}, {"id": "cleaning_service_cleaningservice_apply_action", "label": ".apply_action()", "file_type": "code", "source_file": "D:\\RL-PROJECT\\data-cleaning-openenv\\backend\\services\\cleaning_service.py", "source_location": "L128"}, {"id": "cleaning_service_cleaningservice_calculate_metrics", "label": ".calculate_metrics()", "file_type": "code", "source_file": "D:\\RL-PROJECT\\data-cleaning-openenv\\backend\\services\\cleaning_service.py", "source_location": "L139"}, {"id": "cleaning_service_cleaningservice_load_dataset", "label": "._load_dataset()", "file_type": "code", "source_file": "D:\\RL-PROJECT\\data-cleaning-openenv\\backend\\services\\cleaning_service.py", "source_location": "L171"}, {"id": "cleaning_service_cleaningservice_build_observation", "label": "._build_observation()", "file_type": "code", "source_file": "D:\\RL-PROJECT\\data-cleaning-openenv\\backend\\services\\cleaning_service.py", "source_location": "L182"}, {"id": "cleaning_service_cleaningservice_calculate_reward", "label": "._calculate_reward()", "file_type": "code", "source_file": "D:\\RL-PROJECT\\data-cleaning-openenv\\backend\\services\\cleaning_service.py", "source_location": "L191"}, {"id": "cleaning_service_cleaningservice_create_audit_log", "label": "._create_audit_log()", "file_type": "code", "source_file": "D:\\RL-PROJECT\\data-cleaning-openenv\\backend\\services\\cleaning_service.py", "source_location": "L196"}, {"id": "cleaning_service_cleaningservice_infer_agent_name", "label": "._infer_agent_name()", "file_type": "code", "source_file": "D:\\RL-PROJECT\\data-cleaning-openenv\\backend\\services\\cleaning_service.py", "source_location": "L220"}, {"id": "cleaning_service_rationale_1", "label": "Core cleaning service orchestration logic.", "file_type": "rationale", "source_file": "D:\\RL-PROJECT\\data-cleaning-openenv\\backend\\services\\cleaning_service.py", "source_location": "L1"}, {"id": "cleaning_service_rationale_29", "label": "Service layer for batch and interactive cleaning operations.", "file_type": "rationale", "source_file": "D:\\RL-PROJECT\\data-cleaning-openenv\\backend\\services\\cleaning_service.py", "source_location": "L29"}, {"id": "cleaning_service_rationale_36", "label": "Execute cleaning lifecycle against an existing queued job.", "file_type": "rationale", "source_file": "D:\\RL-PROJECT\\data-cleaning-openenv\\backend\\services\\cleaning_service.py", "source_location": "L36"}, {"id": "cleaning_service_rationale_86", "label": "Run full-batch cleaning orchestration and return persisted job state.", "file_type": "rationale", "source_file": "D:\\RL-PROJECT\\data-cleaning-openenv\\backend\\services\\cleaning_service.py", "source_location": "L86"}, {"id": "cleaning_service_rationale_109", "label": "Return next suggested action for interactive flow.", "file_type": "rationale", "source_file": "D:\\RL-PROJECT\\data-cleaning-openenv\\backend\\services\\cleaning_service.py", "source_location": "L109"}, {"id": "cleaning_service_rationale_129", "label": "Persist action into audit logs and return reward payload.", "file_type": "rationale", "source_file": "D:\\RL-PROJECT\\data-cleaning-openenv\\backend\\services\\cleaning_service.py", "source_location": "L129"}, {"id": "cleaning_service_rationale_140", "label": "Calculate before/after quality metrics for dataset.", "file_type": "rationale", "source_file": "D:\\RL-PROJECT\\data-cleaning-openenv\\backend\\services\\cleaning_service.py", "source_location": "L140"}], "edges": [{"source": "d_rl_project_data_cleaning_openenv_backend_services_cleaning_service_py", "target": "logging", "relation": "imports", "confidence": "EXTRACTED", "source_file": "D:\\RL-PROJECT\\data-cleaning-openenv\\backend\\services\\cleaning_service.py", "source_location": "L5", "weight": 1.0}, {"source": "d_rl_project_data_cleaning_openenv_backend_services_cleaning_service_py", "target": "datetime", "relation": "imports_from", "confidence": "EXTRACTED", "source_file": "D:\\RL-PROJECT\\data-cleaning-openenv\\backend\\services\\cleaning_service.py", "source_location": "L6", "weight": 1.0}, {"source": "d_rl_project_data_cleaning_openenv_backend_services_cleaning_service_py", "target": "pathlib", "relation": "imports_from", "confidence": "EXTRACTED", "source_file": "D:\\RL-PROJECT\\data-cleaning-openenv\\backend\\services\\cleaning_service.py", "source_location": "L7", "weight": 1.0}, {"source": "d_rl_project_data_cleaning_openenv_backend_services_cleaning_service_py", "target": "typing", "relation": "imports_from", "confidence": "EXTRACTED", "source_file": "D:\\RL-PROJECT\\data-cleaning-openenv\\backend\\services\\cleaning_service.py", "source_location": "L8", "weight": 1.0}, {"source": "d_rl_project_data_cleaning_openenv_backend_services_cleaning_service_py", "target": "uuid", "relation": "imports_from", "confidence": "EXTRACTED", "source_file": "D:\\RL-PROJECT\\data-cleaning-openenv\\backend\\services\\cleaning_service.py", "source_location": "L9", "weight": 1.0}, {"source": "d_rl_project_data_cleaning_openenv_backend_services_cleaning_service_py", "target": "pandas", "relation": "imports", "confidence": "EXTRACTED", "source_file": "D:\\RL-PROJECT\\data-cleaning-openenv\\backend\\services\\cleaning_service.py", "source_location": "L11", "weight": 1.0}, {"source": "d_rl_project_data_cleaning_openenv_backend_services_cleaning_service_py", "target": "sqlalchemy_orm", "relation": "imports_from", "confidence": "EXTRACTED", "source_file": "D:\\RL-PROJECT\\data-cleaning-openenv\\backend\\services\\cleaning_service.py", "source_location": "L12", "weight": 1.0}, {"source": "d_rl_project_data_cleaning_openenv_backend_services_cleaning_service_py", "target": "backend_ml_agent_coordinator", "relation": "imports_from", "confidence": "EXTRACTED", "source_file": "D:\\RL-PROJECT\\data-cleaning-openenv\\backend\\services\\cleaning_service.py", "source_location": "L14", "weight": 1.0}, {"source": "d_rl_project_data_cleaning_openenv_backend_services_cleaning_service_py", "target": "backend_monitoring_metrics", "relation": "imports_from", "confidence": "EXTRACTED", "source_file": "D:\\RL-PROJECT\\data-cleaning-openenv\\backend\\services\\cleaning_service.py", "source_location": "L15", "weight": 1.0}, {"source": "d_rl_project_data_cleaning_openenv_backend_services_cleaning_service_py", "target": "backend_models_audit_log", "relation": "imports_from", "confidence": "EXTRACTED", "source_file": "D:\\RL-PROJECT\\data-cleaning-openenv\\backend\\services\\cleaning_service.py", "source_location": "L21", "weight": 1.0}, {"source": "d_rl_project_data_cleaning_openenv_backend_services_cleaning_service_py", "target": "backend_models_cleaning_job", "relation": "imports_from", "confidence": "EXTRACTED", "source_file": "D:\\RL-PROJECT\\data-cleaning-openenv\\backend\\services\\cleaning_service.py", "source_location": "L22", "weight": 1.0}, {"source": "d_rl_project_data_cleaning_openenv_backend_services_cleaning_service_py", "target": "backend_models_dataset", "relation": "imports_from", "confidence": "EXTRACTED", "source_file": "D:\\RL-PROJECT\\data-cleaning-openenv\\backend\\services\\cleaning_service.py", "source_location": "L23", "weight": 1.0}, {"source": "d_rl_project_data_cleaning_openenv_backend_services_cleaning_service_py", "target": "cleaning_service_cleaningservice", "relation": "contains", "confidence": "EXTRACTED", "source_file": "D:\\RL-PROJECT\\data-cleaning-openenv\\backend\\services\\cleaning_service.py", "source_location": "L28", "weight": 1.0}, {"source": "cleaning_service_cleaningservice", "target": "cleaning_service_cleaningservice_init", "relation": "method", "confidence": "EXTRACTED", "source_file": "D:\\RL-PROJECT\\data-cleaning-openenv\\backend\\services\\cleaning_service.py", "source_location": "L31", "weight": 1.0}, {"source": "cleaning_service_cleaningservice", "target": "cleaning_service_cleaningservice_clean_existing_job", "relation": "method", "confidence": "EXTRACTED", "source_file": "D:\\RL-PROJECT\\data-cleaning-openenv\\backend\\services\\cleaning_service.py", "source_location": "L35", "weight": 1.0}, {"source": "cleaning_service_cleaningservice", "target": "cleaning_service_cleaningservice_clean_batch", "relation": "method", "confidence": "EXTRACTED", "source_file": "D:\\RL-PROJECT\\data-cleaning-openenv\\backend\\services\\cleaning_service.py", "source_location": "L85", "weight": 1.0}, {"source": "cleaning_service_cleaningservice", "target": "cleaning_service_cleaningservice_get_next_action", "relation": "method", "confidence": "EXTRACTED", "source_file": "D:\\RL-PROJECT\\data-cleaning-openenv\\backend\\services\\cleaning_service.py", "source_location": "L103", "weight": 1.0}, {"source": "cleaning_service_cleaningservice", "target": "cleaning_service_cleaningservice_apply_action", "relation": "method", "confidence": "EXTRACTED", "source_file": "D:\\RL-PROJECT\\data-cleaning-openenv\\backend\\services\\cleaning_service.py", "source_location": "L128", "weight": 1.0}, {"source": "cleaning_service_cleaningservice", "target": "cleaning_service_cleaningservice_calculate_metrics", "relation": "method", "confidence": "EXTRACTED", "source_file": "D:\\RL-PROJECT\\data-cleaning-openenv\\backend\\services\\cleaning_service.py", "source_location": "L139", "weight": 1.0}, {"source": "cleaning_service_cleaningservice", "target": "cleaning_service_cleaningservice_load_dataset", "relation": "method", "confidence": "EXTRACTED", "source_file": "D:\\RL-PROJECT\\data-cleaning-openenv\\backend\\services\\cleaning_service.py", "source_location": "L171", "weight": 1.0}, {"source": "cleaning_service_cleaningservice", "target": "cleaning_service_cleaningservice_build_observation", "relation": "method", "confidence": "EXTRACTED", "source_file": "D:\\RL-PROJECT\\data-cleaning-openenv\\backend\\services\\cleaning_service.py", "source_location": "L182", "weight": 1.0}, {"source": "cleaning_service_cleaningservice", "target": "cleaning_service_cleaningservice_calculate_reward", "relation": "method", "confidence": "EXTRACTED", "source_file": "D:\\RL-PROJECT\\data-cleaning-openenv\\backend\\services\\cleaning_service.py", "source_location": "L191", "weight": 1.0}, {"source": "cleaning_service_cleaningservice", "target": "cleaning_service_cleaningservice_create_audit_log", "relation": "method", "confidence": "EXTRACTED", "source_file": "D:\\RL-PROJECT\\data-cleaning-openenv\\backend\\services\\cleaning_service.py", "source_location": "L196", "weight": 1.0}, {"source": "cleaning_service_cleaningservice", "target": "cleaning_service_cleaningservice_infer_agent_name", "relation": "method", "confidence": "EXTRACTED", "source_file": "D:\\RL-PROJECT\\data-cleaning-openenv\\backend\\services\\cleaning_service.py", "source_location": "L220", "weight": 1.0}, {"source": "cleaning_service_cleaningservice_clean_existing_job", "target": "cleaning_service_cleaningservice_load_dataset", "relation": "calls", "confidence": "EXTRACTED", "source_file": "D:\\RL-PROJECT\\data-cleaning-openenv\\backend\\services\\cleaning_service.py", "source_location": "L50", "weight": 1.0}, {"source": "cleaning_service_cleaningservice_clean_existing_job", "target": "cleaning_service_cleaningservice_build_observation", "relation": "calls", "confidence": "EXTRACTED", "source_file": "D:\\RL-PROJECT\\data-cleaning-openenv\\backend\\services\\cleaning_service.py", "source_location": "L54", "weight": 1.0}, {"source": "cleaning_service_cleaningservice_clean_existing_job", "target": "cleaning_service_cleaningservice_calculate_reward", "relation": "calls", "confidence": "EXTRACTED", "source_file": "D:\\RL-PROJECT\\data-cleaning-openenv\\backend\\services\\cleaning_service.py", "source_location": "L56", "weight": 1.0}, {"source": "cleaning_service_cleaningservice_clean_existing_job", "target": "cleaning_service_cleaningservice_create_audit_log", "relation": "calls", "confidence": "EXTRACTED", "source_file": "D:\\RL-PROJECT\\data-cleaning-openenv\\backend\\services\\cleaning_service.py", "source_location": "L60", "weight": 1.0}, {"source": "cleaning_service_cleaningservice_clean_existing_job", "target": "cleaning_service_cleaningservice_calculate_metrics", "relation": "calls", "confidence": "EXTRACTED", "source_file": "D:\\RL-PROJECT\\data-cleaning-openenv\\backend\\services\\cleaning_service.py", "source_location": "L65", "weight": 1.0}, {"source": "cleaning_service_cleaningservice_clean_batch", "target": "cleaning_service_cleaningservice_clean_existing_job", "relation": "calls", "confidence": "EXTRACTED", "source_file": "D:\\RL-PROJECT\\data-cleaning-openenv\\backend\\services\\cleaning_service.py", "source_location": "L101", "weight": 1.0}, {"source": "cleaning_service_cleaningservice_get_next_action", "target": "cleaning_service_cleaningservice_infer_agent_name", "relation": "calls", "confidence": "EXTRACTED", "source_file": "D:\\RL-PROJECT\\data-cleaning-openenv\\backend\\services\\cleaning_service.py", "source_location": "L124", "weight": 1.0}, {"source": "cleaning_service_cleaningservice_apply_action", "target": "cleaning_service_cleaningservice_calculate_reward", "relation": "calls", "confidence": "EXTRACTED", "source_file": "D:\\RL-PROJECT\\data-cleaning-openenv\\backend\\services\\cleaning_service.py", "source_location": "L134", "weight": 1.0}, {"source": "cleaning_service_cleaningservice_apply_action", "target": "cleaning_service_cleaningservice_create_audit_log", "relation": "calls", "confidence": "EXTRACTED", "source_file": "D:\\RL-PROJECT\\data-cleaning-openenv\\backend\\services\\cleaning_service.py", "source_location": "L135", "weight": 1.0}, {"source": "cleaning_service_cleaningservice_calculate_metrics", "target": "cleaning_service_cleaningservice_load_dataset", "relation": "calls", "confidence": "EXTRACTED", "source_file": "D:\\RL-PROJECT\\data-cleaning-openenv\\backend\\services\\cleaning_service.py", "source_location": "L145", "weight": 1.0}, {"source": "cleaning_service_cleaningservice_create_audit_log", "target": "cleaning_service_cleaningservice_infer_agent_name", "relation": "calls", "confidence": "EXTRACTED", "source_file": "D:\\RL-PROJECT\\data-cleaning-openenv\\backend\\services\\cleaning_service.py", "source_location": "L211", "weight": 1.0}, {"source": "cleaning_service_rationale_1", "target": "d_rl_project_data_cleaning_openenv_backend_services_cleaning_service_py", "relation": "rationale_for", "confidence": "EXTRACTED", "source_file": "D:\\RL-PROJECT\\data-cleaning-openenv\\backend\\services\\cleaning_service.py", "source_location": "L1", "weight": 1.0}, {"source": "cleaning_service_rationale_29", "target": "cleaning_service_cleaningservice", "relation": "rationale_for", "confidence": "EXTRACTED", "source_file": "D:\\RL-PROJECT\\data-cleaning-openenv\\backend\\services\\cleaning_service.py", "source_location": "L29", "weight": 1.0}, {"source": "cleaning_service_rationale_36", "target": "cleaning_service_cleaningservice_clean_existing_job", "relation": "rationale_for", "confidence": "EXTRACTED", "source_file": "D:\\RL-PROJECT\\data-cleaning-openenv\\backend\\services\\cleaning_service.py", "source_location": "L36", "weight": 1.0}, {"source": "cleaning_service_rationale_86", "target": "cleaning_service_cleaningservice_clean_batch", "relation": "rationale_for", "confidence": "EXTRACTED", "source_file": "D:\\RL-PROJECT\\data-cleaning-openenv\\backend\\services\\cleaning_service.py", "source_location": "L86", "weight": 1.0}, {"source": "cleaning_service_rationale_109", "target": "cleaning_service_cleaningservice_get_next_action", "relation": "rationale_for", "confidence": "EXTRACTED", "source_file": "D:\\RL-PROJECT\\data-cleaning-openenv\\backend\\services\\cleaning_service.py", "source_location": "L109", "weight": 1.0}, {"source": "cleaning_service_rationale_129", "target": "cleaning_service_cleaningservice_apply_action", "relation": "rationale_for", "confidence": "EXTRACTED", "source_file": "D:\\RL-PROJECT\\data-cleaning-openenv\\backend\\services\\cleaning_service.py", "source_location": "L129", "weight": 1.0}, {"source": "cleaning_service_rationale_140", "target": "cleaning_service_cleaningservice_calculate_metrics", "relation": "rationale_for", "confidence": "EXTRACTED", "source_file": "D:\\RL-PROJECT\\data-cleaning-openenv\\backend\\services\\cleaning_service.py", "source_location": "L140", "weight": 1.0}], "raw_calls": [{"caller_nid": "cleaning_service_cleaningservice_init", "callee": "AgentCoordinator", "source_file": "D:\\RL-PROJECT\\data-cleaning-openenv\\backend\\services\\cleaning_service.py", "source_location": "L33"}, {"caller_nid": "cleaning_service_cleaningservice_clean_existing_job", "callee": "get", "source_file": "D:\\RL-PROJECT\\data-cleaning-openenv\\backend\\services\\cleaning_service.py", "source_location": "L37"}, {"caller_nid": "cleaning_service_cleaningservice_clean_existing_job", "callee": "ValueError", "source_file": "D:\\RL-PROJECT\\data-cleaning-openenv\\backend\\services\\cleaning_service.py", "source_location": "L39"}, {"caller_nid": "cleaning_service_cleaningservice_clean_existing_job", "callee": "track_cleaning_job_duration", "source_file": "D:\\RL-PROJECT\\data-cleaning-openenv\\backend\\services\\cleaning_service.py", "source_location": "L41"}, {"caller_nid": "cleaning_service_cleaningservice_clean_existing_job", "callee": "now", "source_file": "D:\\RL-PROJECT\\data-cleaning-openenv\\backend\\services\\cleaning_service.py", "source_location": "L44"}, {"caller_nid": "cleaning_service_cleaningservice_clean_existing_job", "callee": "flush", "source_file": "D:\\RL-PROJECT\\data-cleaning-openenv\\backend\\services\\cleaning_service.py", "source_location": "L48"}, {"caller_nid": "cleaning_service_cleaningservice_clean_existing_job", "callee": "enumerate", "source_file": "D:\\RL-PROJECT\\data-cleaning-openenv\\backend\\services\\cleaning_service.py", "source_location": "L53"}, {"caller_nid": "cleaning_service_cleaningservice_clean_existing_job", "callee": "iterrows", "source_file": "D:\\RL-PROJECT\\data-cleaning-openenv\\backend\\services\\cleaning_service.py", "source_location": "L53"}, {"caller_nid": "cleaning_service_cleaningservice_clean_existing_job", "callee": "to_dict", "source_file": "D:\\RL-PROJECT\\data-cleaning-openenv\\backend\\services\\cleaning_service.py", "source_location": "L54"}, {"caller_nid": "cleaning_service_cleaningservice_clean_existing_job", "callee": "get_best_action", "source_file": "D:\\RL-PROJECT\\data-cleaning-openenv\\backend\\services\\cleaning_service.py", "source_location": "L55"}, {"caller_nid": "cleaning_service_cleaningservice_clean_existing_job", "callee": "update_agent_performance", "source_file": "D:\\RL-PROJECT\\data-cleaning-openenv\\backend\\services\\cleaning_service.py", "source_location": "L57"}, {"caller_nid": "cleaning_service_cleaningservice_clean_existing_job", "callee": "get", "source_file": "D:\\RL-PROJECT\\data-cleaning-openenv\\backend\\services\\cleaning_service.py", "source_location": "L58"}, {"caller_nid": "cleaning_service_cleaningservice_clean_existing_job", "callee": "flush", "source_file": "D:\\RL-PROJECT\\data-cleaning-openenv\\backend\\services\\cleaning_service.py", "source_location": "L63"}, {"caller_nid": "cleaning_service_cleaningservice_clean_existing_job", "callee": "now", "source_file": "D:\\RL-PROJECT\\data-cleaning-openenv\\backend\\services\\cleaning_service.py", "source_location": "L69"}, {"caller_nid": "cleaning_service_cleaningservice_clean_existing_job", "callee": "get_agent_statistics", "source_file": "D:\\RL-PROJECT\\data-cleaning-openenv\\backend\\services\\cleaning_service.py", "source_location": "L74"}, {"caller_nid": "cleaning_service_cleaningservice_clean_existing_job", "callee": "set", "source_file": "D:\\RL-PROJECT\\data-cleaning-openenv\\backend\\services\\cleaning_service.py", "source_location": "L76"}, {"caller_nid": "cleaning_service_cleaningservice_clean_existing_job", "callee": "labels", "source_file": "D:\\RL-PROJECT\\data-cleaning-openenv\\backend\\services\\cleaning_service.py", "source_location": "L76"}, {"caller_nid": "cleaning_service_cleaningservice_clean_existing_job", "callee": "commit", "source_file": "D:\\RL-PROJECT\\data-cleaning-openenv\\backend\\services\\cleaning_service.py", "source_location": "L78"}, {"caller_nid": "cleaning_service_cleaningservice_clean_existing_job", "callee": "refresh", "source_file": "D:\\RL-PROJECT\\data-cleaning-openenv\\backend\\services\\cleaning_service.py", "source_location": "L79"}, {"caller_nid": "cleaning_service_cleaningservice_clean_batch", "callee": "get", "source_file": "D:\\RL-PROJECT\\data-cleaning-openenv\\backend\\services\\cleaning_service.py", "source_location": "L87"}, {"caller_nid": "cleaning_service_cleaningservice_clean_batch", "callee": "ValueError", "source_file": "D:\\RL-PROJECT\\data-cleaning-openenv\\backend\\services\\cleaning_service.py", "source_location": "L89"}, {"caller_nid": "cleaning_service_cleaningservice_clean_batch", "callee": "CleaningJob", "source_file": "D:\\RL-PROJECT\\data-cleaning-openenv\\backend\\services\\cleaning_service.py", "source_location": "L91"}, {"caller_nid": "cleaning_service_cleaningservice_clean_batch", "callee": "now", "source_file": "D:\\RL-PROJECT\\data-cleaning-openenv\\backend\\services\\cleaning_service.py", "source_location": "L96"}, {"caller_nid": "cleaning_service_cleaningservice_clean_batch", "callee": "add", "source_file": "D:\\RL-PROJECT\\data-cleaning-openenv\\backend\\services\\cleaning_service.py", "source_location": "L99"}, {"caller_nid": "cleaning_service_cleaningservice_clean_batch", "callee": "flush", "source_file": "D:\\RL-PROJECT\\data-cleaning-openenv\\backend\\services\\cleaning_service.py", "source_location": "L100"}, {"caller_nid": "cleaning_service_cleaningservice_get_next_action", "callee": "get", "source_file": "D:\\RL-PROJECT\\data-cleaning-openenv\\backend\\services\\cleaning_service.py", "source_location": "L110"}, {"caller_nid": "cleaning_service_cleaningservice_get_next_action", "callee": "ValueError", "source_file": "D:\\RL-PROJECT\\data-cleaning-openenv\\backend\\services\\cleaning_service.py", "source_location": "L112"}, {"caller_nid": "cleaning_service_cleaningservice_get_next_action", "callee": "track_inference_latency", "source_file": "D:\\RL-PROJECT\\data-cleaning-openenv\\backend\\services\\cleaning_service.py", "source_location": "L119"}, {"caller_nid": "cleaning_service_cleaningservice_get_next_action", "callee": "get_best_action", "source_file": "D:\\RL-PROJECT\\data-cleaning-openenv\\backend\\services\\cleaning_service.py", "source_location": "L120"}, {"caller_nid": "cleaning_service_cleaningservice_apply_action", "callee": "get", "source_file": "D:\\RL-PROJECT\\data-cleaning-openenv\\backend\\services\\cleaning_service.py", "source_location": "L130"}, {"caller_nid": "cleaning_service_cleaningservice_apply_action", "callee": "ValueError", "source_file": "D:\\RL-PROJECT\\data-cleaning-openenv\\backend\\services\\cleaning_service.py", "source_location": "L132"}, {"caller_nid": "cleaning_service_cleaningservice_apply_action", "callee": "get", "source_file": "D:\\RL-PROJECT\\data-cleaning-openenv\\backend\\services\\cleaning_service.py", "source_location": "L134"}, {"caller_nid": "cleaning_service_cleaningservice_apply_action", "callee": "commit", "source_file": "D:\\RL-PROJECT\\data-cleaning-openenv\\backend\\services\\cleaning_service.py", "source_location": "L136"}, {"caller_nid": "cleaning_service_cleaningservice_calculate_metrics", "callee": "get", "source_file": "D:\\RL-PROJECT\\data-cleaning-openenv\\backend\\services\\cleaning_service.py", "source_location": "L141"}, {"caller_nid": "cleaning_service_cleaningservice_calculate_metrics", "callee": "ValueError", "source_file": "D:\\RL-PROJECT\\data-cleaning-openenv\\backend\\services\\cleaning_service.py", "source_location": "L143"}, {"caller_nid": "cleaning_service_cleaningservice_calculate_metrics", "callee": "max", "source_file": "D:\\RL-PROJECT\\data-cleaning-openenv\\backend\\services\\cleaning_service.py", "source_location": "L146"}, {"caller_nid": "cleaning_service_cleaningservice_calculate_metrics", "callee": "max", "source_file": "D:\\RL-PROJECT\\data-cleaning-openenv\\backend\\services\\cleaning_service.py", "source_location": "L146"}, {"caller_nid": "cleaning_service_cleaningservice_calculate_metrics", "callee": "int", "source_file": "D:\\RL-PROJECT\\data-cleaning-openenv\\backend\\services\\cleaning_service.py", "source_location": "L147"}, {"caller_nid": "cleaning_service_cleaningservice_calculate_metrics", "callee": "sum", "source_file": "D:\\RL-PROJECT\\data-cleaning-openenv\\backend\\services\\cleaning_service.py", "source_location": "L147"}, {"caller_nid": "cleaning_service_cleaningservice_calculate_metrics", "callee": "sum", "source_file": "D:\\RL-PROJECT\\data-cleaning-openenv\\backend\\services\\cleaning_service.py", "source_location": "L147"}, {"caller_nid": "cleaning_service_cleaningservice_calculate_metrics", "callee": "isna", "source_file": "D:\\RL-PROJECT\\data-cleaning-openenv\\backend\\services\\cleaning_service.py", "source_location": "L147"}, {"caller_nid": "cleaning_service_cleaningservice_calculate_metrics", "callee": "int", "source_file": "D:\\RL-PROJECT\\data-cleaning-openenv\\backend\\services\\cleaning_service.py", "source_location": "L148"}, {"caller_nid": "cleaning_service_cleaningservice_calculate_metrics", "callee": "sum", "source_file": "D:\\RL-PROJECT\\data-cleaning-openenv\\backend\\services\\cleaning_service.py", "source_location": "L148"}, {"caller_nid": "cleaning_service_cleaningservice_calculate_metrics", "callee": "duplicated", "source_file": "D:\\RL-PROJECT\\data-cleaning-openenv\\backend\\services\\cleaning_service.py", "source_location": "L148"}, {"caller_nid": "cleaning_service_cleaningservice_calculate_metrics", "callee": "max", "source_file": "D:\\RL-PROJECT\\data-cleaning-openenv\\backend\\services\\cleaning_service.py", "source_location": "L150"}, {"caller_nid": "cleaning_service_cleaningservice_calculate_metrics", "callee": "min", "source_file": "D:\\RL-PROJECT\\data-cleaning-openenv\\backend\\services\\cleaning_service.py", "source_location": "L150"}, {"caller_nid": "cleaning_service_cleaningservice_calculate_metrics", "callee": "max", "source_file": "D:\\RL-PROJECT\\data-cleaning-openenv\\backend\\services\\cleaning_service.py", "source_location": "L150"}, {"caller_nid": "cleaning_service_cleaningservice_calculate_metrics", "callee": "len", "source_file": "D:\\RL-PROJECT\\data-cleaning-openenv\\backend\\services\\cleaning_service.py", "source_location": "L150"}, {"caller_nid": "cleaning_service_cleaningservice_calculate_metrics", "callee": "max", "source_file": "D:\\RL-PROJECT\\data-cleaning-openenv\\backend\\services\\cleaning_service.py", "source_location": "L152"}, {"caller_nid": "cleaning_service_cleaningservice_calculate_metrics", "callee": "max", "source_file": "D:\\RL-PROJECT\\data-cleaning-openenv\\backend\\services\\cleaning_service.py", "source_location": "L153"}, {"caller_nid": "cleaning_service_cleaningservice_calculate_metrics", "callee": "int", "source_file": "D:\\RL-PROJECT\\data-cleaning-openenv\\backend\\services\\cleaning_service.py", "source_location": "L153"}, {"caller_nid": "cleaning_service_cleaningservice_calculate_metrics", "callee": "max", "source_file": "D:\\RL-PROJECT\\data-cleaning-openenv\\backend\\services\\cleaning_service.py", "source_location": "L154"}, {"caller_nid": "cleaning_service_cleaningservice_calculate_metrics", "callee": "min", "source_file": "D:\\RL-PROJECT\\data-cleaning-openenv\\backend\\services\\cleaning_service.py", "source_location": "L154"}, {"caller_nid": "cleaning_service_cleaningservice_calculate_metrics", "callee": "max", "source_file": "D:\\RL-PROJECT\\data-cleaning-openenv\\backend\\services\\cleaning_service.py", "source_location": "L156"}, {"caller_nid": "cleaning_service_cleaningservice_calculate_metrics", "callee": "min", "source_file": "D:\\RL-PROJECT\\data-cleaning-openenv\\backend\\services\\cleaning_service.py", "source_location": "L156"}, {"caller_nid": "cleaning_service_cleaningservice_calculate_metrics", "callee": "round", "source_file": "D:\\RL-PROJECT\\data-cleaning-openenv\\backend\\services\\cleaning_service.py", "source_location": "L159"}, {"caller_nid": "cleaning_service_cleaningservice_calculate_metrics", "callee": "round", "source_file": "D:\\RL-PROJECT\\data-cleaning-openenv\\backend\\services\\cleaning_service.py", "source_location": "L161"}, {"caller_nid": "cleaning_service_cleaningservice_calculate_metrics", "callee": "round", "source_file": "D:\\RL-PROJECT\\data-cleaning-openenv\\backend\\services\\cleaning_service.py", "source_location": "L164"}, {"caller_nid": "cleaning_service_cleaningservice_calculate_metrics", "callee": "round", "source_file": "D:\\RL-PROJECT\\data-cleaning-openenv\\backend\\services\\cleaning_service.py", "source_location": "L166"}, {"caller_nid": "cleaning_service_cleaningservice_calculate_metrics", "callee": "round", "source_file": "D:\\RL-PROJECT\\data-cleaning-openenv\\backend\\services\\cleaning_service.py", "source_location": "L168"}, {"caller_nid": "cleaning_service_cleaningservice_load_dataset", "callee": "Path", "source_file": "D:\\RL-PROJECT\\data-cleaning-openenv\\backend\\services\\cleaning_service.py", "source_location": "L172"}, {"caller_nid": "cleaning_service_cleaningservice_load_dataset", "callee": "exists", "source_file": "D:\\RL-PROJECT\\data-cleaning-openenv\\backend\\services\\cleaning_service.py", "source_location": "L173"}, {"caller_nid": "cleaning_service_cleaningservice_load_dataset", "callee": "ValueError", "source_file": "D:\\RL-PROJECT\\data-cleaning-openenv\\backend\\services\\cleaning_service.py", "source_location": "L174"}, {"caller_nid": "cleaning_service_cleaningservice_load_dataset", "callee": "lower", "source_file": "D:\\RL-PROJECT\\data-cleaning-openenv\\backend\\services\\cleaning_service.py", "source_location": "L175"}, {"caller_nid": "cleaning_service_cleaningservice_load_dataset", "callee": "read_csv", "source_file": "D:\\RL-PROJECT\\data-cleaning-openenv\\backend\\services\\cleaning_service.py", "source_location": "L177"}, {"caller_nid": "cleaning_service_cleaningservice_load_dataset", "callee": "read_excel", "source_file": "D:\\RL-PROJECT\\data-cleaning-openenv\\backend\\services\\cleaning_service.py", "source_location": "L179"}, {"caller_nid": "cleaning_service_cleaningservice_load_dataset", "callee": "ValueError", "source_file": "D:\\RL-PROJECT\\data-cleaning-openenv\\backend\\services\\cleaning_service.py", "source_location": "L180"}, {"caller_nid": "cleaning_service_cleaningservice_build_observation", "callee": "items", "source_file": "D:\\RL-PROJECT\\data-cleaning-openenv\\backend\\services\\cleaning_service.py", "source_location": "L184"}, {"caller_nid": "cleaning_service_cleaningservice_build_observation", "callee": "isinstance", "source_file": "D:\\RL-PROJECT\\data-cleaning-openenv\\backend\\services\\cleaning_service.py", "source_location": "L185"}, {"caller_nid": "cleaning_service_cleaningservice_build_observation", "callee": "isna", "source_file": "D:\\RL-PROJECT\\data-cleaning-openenv\\backend\\services\\cleaning_service.py", "source_location": "L185"}, {"caller_nid": "cleaning_service_cleaningservice_build_observation", "callee": "append", "source_file": "D:\\RL-PROJECT\\data-cleaning-openenv\\backend\\services\\cleaning_service.py", "source_location": "L186"}, {"caller_nid": "cleaning_service_cleaningservice_build_observation", "callee": "isinstance", "source_file": "D:\\RL-PROJECT\\data-cleaning-openenv\\backend\\services\\cleaning_service.py", "source_location": "L187"}, {"caller_nid": "cleaning_service_cleaningservice_build_observation", "callee": "strip", "source_file": "D:\\RL-PROJECT\\data-cleaning-openenv\\backend\\services\\cleaning_service.py", "source_location": "L187"}, {"caller_nid": "cleaning_service_cleaningservice_build_observation", "callee": "append", "source_file": "D:\\RL-PROJECT\\data-cleaning-openenv\\backend\\services\\cleaning_service.py", "source_location": "L188"}, {"caller_nid": "cleaning_service_cleaningservice_calculate_reward", "callee": "min", "source_file": "D:\\RL-PROJECT\\data-cleaning-openenv\\backend\\services\\cleaning_service.py", "source_location": "L194"}, {"caller_nid": "cleaning_service_cleaningservice_calculate_reward", "callee": "len", "source_file": "D:\\RL-PROJECT\\data-cleaning-openenv\\backend\\services\\cleaning_service.py", "source_location": "L194"}, {"caller_nid": "cleaning_service_cleaningservice_create_audit_log", "callee": "AuditLog", "source_file": "D:\\RL-PROJECT\\data-cleaning-openenv\\backend\\services\\cleaning_service.py", "source_location": "L203"}, {"caller_nid": "cleaning_service_cleaningservice_create_audit_log", "callee": "get", "source_file": "D:\\RL-PROJECT\\data-cleaning-openenv\\backend\\services\\cleaning_service.py", "source_location": "L205"}, {"caller_nid": "cleaning_service_cleaningservice_create_audit_log", "callee": "get", "source_file": "D:\\RL-PROJECT\\data-cleaning-openenv\\backend\\services\\cleaning_service.py", "source_location": "L207"}, {"caller_nid": "cleaning_service_cleaningservice_create_audit_log", "callee": "get", "source_file": "D:\\RL-PROJECT\\data-cleaning-openenv\\backend\\services\\cleaning_service.py", "source_location": "L208"}, {"caller_nid": "cleaning_service_cleaningservice_create_audit_log", "callee": "get", "source_file": "D:\\RL-PROJECT\\data-cleaning-openenv\\backend\\services\\cleaning_service.py", "source_location": "L209"}, {"caller_nid": "cleaning_service_cleaningservice_create_audit_log", "callee": "get", "source_file": "D:\\RL-PROJECT\\data-cleaning-openenv\\backend\\services\\cleaning_service.py", "source_location": "L211"}, {"caller_nid": "cleaning_service_cleaningservice_create_audit_log", "callee": "float", "source_file": "D:\\RL-PROJECT\\data-cleaning-openenv\\backend\\services\\cleaning_service.py", "source_location": "L212"}, {"caller_nid": "cleaning_service_cleaningservice_create_audit_log", "callee": "get", "source_file": "D:\\RL-PROJECT\\data-cleaning-openenv\\backend\\services\\cleaning_service.py", "source_location": "L212"}, {"caller_nid": "cleaning_service_cleaningservice_create_audit_log", "callee": "inc", "source_file": "D:\\RL-PROJECT\\data-cleaning-openenv\\backend\\services\\cleaning_service.py", "source_location": "L214"}, {"caller_nid": "cleaning_service_cleaningservice_create_audit_log", "callee": "labels", "source_file": "D:\\RL-PROJECT\\data-cleaning-openenv\\backend\\services\\cleaning_service.py", "source_location": "L214"}, {"caller_nid": "cleaning_service_cleaningservice_create_audit_log", "callee": "get", "source_file": "D:\\RL-PROJECT\\data-cleaning-openenv\\backend\\services\\cleaning_service.py", "source_location": "L215"}, {"caller_nid": "cleaning_service_cleaningservice_create_audit_log", "callee": "get", "source_file": "D:\\RL-PROJECT\\data-cleaning-openenv\\backend\\services\\cleaning_service.py", "source_location": "L216"}, {"caller_nid": "cleaning_service_cleaningservice_create_audit_log", "callee": "add", "source_file": "D:\\RL-PROJECT\\data-cleaning-openenv\\backend\\services\\cleaning_service.py", "source_location": "L218"}, {"caller_nid": "cleaning_service_cleaningservice_infer_agent_name", "callee": "lower", "source_file": "D:\\RL-PROJECT\\data-cleaning-openenv\\backend\\services\\cleaning_service.py", "source_location": "L221"}, {"caller_nid": "cleaning_service_cleaningservice_infer_agent_name", "callee": "any", "source_file": "D:\\RL-PROJECT\\data-cleaning-openenv\\backend\\services\\cleaning_service.py", "source_location": "L222"}, {"caller_nid": "cleaning_service_cleaningservice_infer_agent_name", "callee": "any", "source_file": "D:\\RL-PROJECT\\data-cleaning-openenv\\backend\\services\\cleaning_service.py", "source_location": "L224"}, {"caller_nid": "cleaning_service_cleaningservice_infer_agent_name", "callee": "any", "source_file": "D:\\RL-PROJECT\\data-cleaning-openenv\\backend\\services\\cleaning_service.py", "source_location": "L226"}, {"caller_nid": "cleaning_service_cleaningservice_infer_agent_name", "callee": "any", "source_file": "D:\\RL-PROJECT\\data-cleaning-openenv\\backend\\services\\cleaning_service.py", "source_location": "L228"}]}